NaiveBayes.py
NaiveBayesGauss-0.0.1.dist-info/LICENSE
NaiveBayesGauss-0.0.1.dist-info/METADATA
NaiveBayesGauss-0.0.1.dist-info/WHEEL
NaiveBayesGauss-0.0.1.dist-info/top_level.txt
NaiveBayesGauss-0.0.1.dist-info/RECORD
