Metadata-Version: 2.1
Name: NaiveBayesGauss
Version: 0.0.1
Summary: A custom implementation of the Naive Bayes Gaussian algorithm
Home-page: https://github.com/ilyanovak/naive-bayes-gauss
Author: Ilya Novak
Author-email: ilyanovak@gmail.com
License: UNKNOWN
Platform: UNKNOWN
Classifier: Framework :: IPython
Classifier: Framework :: Jupyter
Classifier: License :: OSI Approved :: MIT License
Classifier: Programming Language :: Python :: 3.8
Classifier: Topic :: Scientific/Engineering :: Mathematics
Classifier: Topic :: Scientific/Engineering :: Visualization
Requires-Python: >=3.6
